awsorgs/__init__.py
awsorgs/accounts.py
awsorgs/auth.py
awsorgs/loginprofile.py
awsorgs/orgs.py
awsorgs/reports.py
awsorgs/spec.py
awsorgs/utils.py
awsorgs/validator.py
awsorgs/data/email_template
awsorgs/spec_init_data/config.yaml
awsorgs/spec_init_data/spec.d/accounts.yaml
awsorgs/spec_init_data/spec.d/common.yaml
awsorgs/spec_init_data/spec.d/custom_policies.yaml
awsorgs/spec_init_data/spec.d/delegations.yaml
awsorgs/spec_init_data/spec.d/groups.yaml
awsorgs/spec_init_data/spec.d/local_users.yaml
awsorgs/spec_init_data/spec.d/organizational_units.yaml
awsorgs/spec_init_data/spec.d/policy_sets.yaml
awsorgs/spec_init_data/spec.d/service_control_policies.yaml
awsorgs/spec_init_data/spec.d/teams.yaml
awsorgs/spec_init_data/spec.d/users.yaml
awsorgs/tools/__init__.py
awsorgs/tools/accessrole.py
awsorgs/tools/spec_init.py
aws_orgs-0.3.4.dist-info/LICENCE.txt
aws_orgs-0.3.4.dist-info/METADATA
aws_orgs-0.3.4.dist-info/WHEEL
aws_orgs-0.3.4.dist-info/entry_points.txt
aws_orgs-0.3.4.dist-info/top_level.txt
aws_orgs-0.3.4.dist-info/RECORD
