Metadata-Version: 2.1
Name: aws-orgs
Version: 0.3.4
Summary: Tools to manage AWS Organizations
Home-page: https://github.com/ucopacme/aws-orgs
Author: Ashley Gould
Author-email: agould@ucop.edu
License: MIT
Keywords: aws organizations
Platform: UNKNOWN
Classifier: Development Status :: 4 - Beta
Classifier: Intended Audience :: Developers
Classifier: Intended Audience :: System Administrators
Classifier: License :: OSI Approved :: MIT License
Classifier: Programming Language :: Python :: 3.6
Classifier: Programming Language :: Python :: 3.7
Requires-Dist: boto3
Requires-Dist: docopt
Requires-Dist: PyYAML
Requires-Dist: passwordgenerator
Requires-Dist: cerberus
